[
  {
    "id": "28972163d1638f7e",
    "type": "tab",
    "label": "Smart Farm",
    "disabled": false,
    "info": ""
  },
  {
    "id": "bd7b79c3fbf5417a",
    "type": "mqtt in",
    "z": "28972163d1638f7e",
    "name": "Nhận cảm biến",
    "topic": "farm/sensor",
    "qos": "0",
    "datatype": "json",
    "broker": "d4179fb10b941343",
    "nl": false,
    "rap": false,
    "inputs": 0,
    "x": 280,
    "y": 420,
    "wires": [
      [
        "a31199f64a6ad255",
        "b8e99199386b9667",
        "01e7a8e29907dd5c",
        "e57427a9f993e160",
        "b91420f0802c3665",
        "b24a110f89916cc1",
        "f8a1gaugefn01",
        "f8a1gaugefn02",
        "9e2f992ea37b88e9",
        "ef65ccde2a9dc727"
      ]
    ]
  },
  {
    "id": "f8a1gaugefn01",
    "type": "function",
    "z": "28972163d1638f7e",
    "name": "Gauge: nhiệt độ",
    "func": "var p = msg.payload;\nif (typeof p === 'string') { try { p = JSON.parse(p); } catch (e) { return null; } }\nif (!p || typeof p !== 'object') return null;\nvar t = parseFloat(p.temperature);\nif (isNaN(t)) return null;\nmsg.payload = t;\nreturn msg;",
    "outputs": 1,
    "timeout": 0,
    "noerr": 0,
    "initialize": "",
    "finalize": "",
    "libs": [],
    "x": 520,
    "y": 420,
    "wires": [
      [
        "f8a1gaugeui01"
      ]
    ]
  },
  {
    "id": "f8a1gaugefn02",
    "type": "function",
    "z": "28972163d1638f7e",
    "name": "Gauge: độ ẩm",
    "func": "var p = msg.payload;\nif (typeof p === 'string') { try { p = JSON.parse(p); } catch (e) { return null; } }\nif (!p || typeof p !== 'object') return null;\nvar h = parseFloat(p.humidity);\nif (isNaN(h)) return null;\nmsg.payload = h;\nreturn msg;",
    "outputs": 1,
    "timeout": 0,
    "noerr": 0,
    "initialize": "",
    "finalize": "",
    "libs": [],
    "x": 520,
    "y": 460,
    "wires": [
      [
        "f8a1gaugeui02"
      ]
    ]
  },
  {
    "id": "f8a1gaugeui01",
    "type": "ui_gauge",
    "z": "28972163d1638f7e",
    "name": "Gauge nhiệt độ",
    "group": "d2ca79a83590b557",
    "order": 0,
    "width": "3",
    "height": "3",
    "gtype": "gage",
    "title": "Nhiệt độ (°C)",
    "label": "°C",
    "min": "0",
    "max": "100",
    "colors": [
      "#00b050",
      "#e6e600",
      "#ca3838"
    ],
    "seg1": "",
    "seg2": "",
    "className": "",
    "x": 740,
    "y": 420,
    "wires": []
  },
  {
    "id": "f8a1gaugeui02",
    "type": "ui_gauge",
    "z": "28972163d1638f7e",
    "name": "Gauge độ ẩm",
    "group": "d2ca79a83590b557",
    "order": 1,
    "width": "3",
    "height": "3",
    "gtype": "donut",
    "title": "Độ ẩm KK (%)",
    "label": "%",
    "min": "0",
    "max": "100",
    "colors": [
      "#00b050",
      "#ff9900",
      "#ca3838"
    ],
    "seg1": "",
    "seg2": "",
    "className": "",
    "x": 740,
    "y": 460,
    "wires": []
  },
  {
    "id": "b91420f0802c3665",
    "type": "function",
    "z": "28972163d1638f7e",
    "name": "Chart: nhiệt độ (số)",
    "func": "var p = msg.payload;\nif (typeof p === 'string') { try { p = JSON.parse(p); } catch (e) { return null; } }\nif (!p || typeof p !== 'object') return null;\nvar t = parseFloat(p.temperature);\nif (isNaN(t)) return null;\nmsg.payload = t;\nmsg.topic = 'Nhiệt độ °C';\nreturn msg;",
    "outputs": 1,
    "timeout": 0,
    "noerr": 0,
    "initialize": "",
    "finalize": "",
    "libs": [],
    "x": 520,
    "y": 500,
    "wires": [
      [
        "cc5a9fcda823fb39"
      ]
    ]
  },
  {
    "id": "b24a110f89916cc1",
    "type": "function",
    "z": "28972163d1638f7e",
    "name": "Chart: độ ẩm (số)",
    "func": "var p = msg.payload;\nif (typeof p === 'string') { try { p = JSON.parse(p); } catch (e) { return null; } }\nif (!p || typeof p !== 'object') return null;\nvar h = parseFloat(p.humidity);\nif (isNaN(h)) return null;\nmsg.payload = h;\nmsg.topic = 'Độ ẩm %';\nreturn msg;",
    "outputs": 1,
    "timeout": 0,
    "noerr": 0,
    "initialize": "",
    "finalize": "",
    "libs": [],
    "x": 520,
    "y": 540,
    "wires": [
      [
        "2c3a97d97ea9da30"
      ]
    ]
  },
  {
    "id": "a31199f64a6ad255",
    "type": "switch",
    "z": "28972163d1638f7e",
    "name": "Nhiệt độ > 35°C",
    "property": "payload.temperature",
    "propertyType": "msg",
    "rules": [
      {
        "t": "gt",
        "v": "35",
        "vt": "num"
      }
    ],
    "checkall": "true",
    "repair": false,
    "outputs": 1,
    "x": 560,
    "y": 280,
    "wires": [
      [
        "f9a1toastfn01"
      ]
    ]
  },
  {
    "id": "f9a1toastfn01",
    "type": "function",
    "z": "28972163d1638f7e",
    "name": "Toast text: nhiệt",
    "func": "var p = msg.payload;\nif (typeof p === 'string') { try { p = JSON.parse(p); } catch (e) { return null; } }\nvar t = p && p.temperature != null ? Number(p.temperature) : NaN;\nif (isNaN(t)) return null;\nmsg.payload = '⚠️ Nhiệt độ cao: ' + t + '°C';\nreturn msg;",
    "outputs": 1,
    "timeout": 0,
    "noerr": 0,
    "initialize": "",
    "finalize": "",
    "libs": [],
    "x": 720,
    "y": 280,
    "wires": [
      [
        "425f5a8bf7c2a0b5"
      ]
    ]
  },
  {
    "id": "425f5a8bf7c2a0b5",
    "type": "ui_toast",
    "z": "28972163d1638f7e",
    "position": "top right",
    "displayTime": "8",
    "outputs": 0,
    "name": "Thông báo nhiệt độ",
    "group": "",
    "order": 0,
    "width": 0,
    "height": 0,
    "text": "{{payload}}",
    "color": "",
    "className": "",
    "x": 950,
    "y": 280,
    "wires": []
  },
  {
    "id": "b8e99199386b9667",
    "type": "switch",
    "z": "28972163d1638f7e",
    "name": "Độ ẩm < 40%",
    "property": "payload.humidity",
    "propertyType": "msg",
    "rules": [
      {
        "t": "lt",
        "v": "40",
        "vt": "num"
      }
    ],
    "checkall": "true",
    "repair": false,
    "outputs": 1,
    "x": 560,
    "y": 360,
    "wires": [
      [
        "f9a1toastfn02",
        "dbb4a8c895814460"
      ]
    ]
  },
  {
    "id": "f9a1toastfn02",
    "type": "function",
    "z": "28972163d1638f7e",
    "name": "Toast text: ẩm",
    "func": "var p = msg.payload;\nif (typeof p === 'string') { try { p = JSON.parse(p); } catch (e) { return null; } }\nvar h = p && p.humidity != null ? Number(p.humidity) : NaN;\nif (isNaN(h)) return null;\nmsg.payload = '🌵 Độ ẩm thấp: ' + h + '% — cân nhắc tưới';\nreturn msg;",
    "outputs": 1,
    "timeout": 0,
    "noerr": 0,
    "initialize": "",
    "finalize": "",
    "libs": [],
    "x": 720,
    "y": 360,
    "wires": [
      [
        "e9272ea0978a6ed1"
      ]
    ]
  },
  {
    "id": "e9272ea0978a6ed1",
    "type": "ui_toast",
    "z": "28972163d1638f7e",
    "position": "top right",
    "displayTime": "8",
    "outputs": 0,
    "name": "Thông báo đất khô",
    "group": "",
    "order": 0,
    "width": 0,
    "height": 0,
    "text": "{{payload}}",
    "color": "",
    "className": "",
    "x": 950,
    "y": 360,
    "wires": []
  },
  {
    "id": "dbb4a8c895814460",
    "type": "switch",
    "z": "28972163d1638f7e",
    "name": "Chế độ tưới tự động",
    "property": "manual",
    "propertyType": "flow",
    "rules": [
      {
        "t": "eq",
        "v": "true",
        "vt": "bool"
      }
    ],
    "checkall": "true",
    "repair": false,
    "outputs": 1,
    "x": 760,
    "y": 440,
    "wires": [
      [
        "df4e79c154d58a50"
      ]
    ]
  },
  {
    "id": "df4e79c154d58a50",
    "type": "change",
    "z": "28972163d1638f7e",
    "name": "Bật bơm 5s",
    "rules": [
      {
        "t": "set",
        "p": "payload",
        "pt": "msg",
        "to": "{\"pump\":true,\"duration\":5}",
        "tot": "json"
      }
    ],
    "action": "",
    "property": "",
    "from": "",
    "to": "",
    "reg": false,
    "x": 1010,
    "y": 440,
    "wires": [
      [
        "52d4228c218a253a"
      ]
    ]
  },
  {
    "id": "01e7a8e29907dd5c",
    "type": "switch",
    "z": "28972163d1638f7e",
    "name": "Ẩm < 45% (cần tưới)",
    "property": "payload.humidity",
    "propertyType": "msg",
    "rules": [
      {
        "t": "lt",
        "v": "45",
        "vt": "num"
      }
    ],
    "checkall": "true",
    "repair": false,
    "outputs": 1,
    "x": 560,
    "y": 600,
    "wires": [
      [
        "c90822af4a63eb54"
      ]
    ]
  },
  {
    "id": "c90822af4a63eb54",
    "type": "function",
    "z": "28972163d1638f7e",
    "name": "Hiện trạng bơm",
    "func": "var h = msg.payload.humidity;\nmsg.payload = '🚿 Cần tưới — độ ẩm KK: ' + (h != null ? h : '?') + '%';\nreturn msg;",
    "outputs": 1,
    "timeout": 0,
    "noerr": 0,
    "initialize": "",
    "finalize": "",
    "libs": [],
    "x": 780,
    "y": 600,
    "wires": [
      [
        "22c86325ecbf70be"
      ]
    ]
  },
  {
    "id": "22c86325ecbf70be",
    "type": "ui_text",
    "z": "28972163d1638f7e",
    "group": "d2ca79a83590b557",
    "order": 6,
    "width": "3",
    "height": "2",
    "name": "Trạng thái tưới",
    "format": "<span style=\"font-size:15px;line-height:1.4\">{{msg.payload}}</span>",
    "layout": "row-center",
    "className": "",
    "style": false,
    "font": "",
    "fontSize": "",
    "color": "#1b5e20",
    "x": 1000,
    "y": 620,
    "wires": []
  },
  {
    "id": "e57427a9f993e160",
    "type": "switch",
    "z": "28972163d1638f7e",
    "name": "Độ ẩm < 20%",
    "property": "payload.humidity",
    "propertyType": "msg",
    "rules": [
      {
        "t": "lt",
        "v": "20",
        "vt": "num"
      }
    ],
    "checkall": "true",
    "repair": false,
    "outputs": 1,
    "x": 560,
    "y": 660,
    "wires": [
      [
        "673687e437ae8622"
      ]
    ]
  },
  {
    "id": "673687e437ae8622",
    "type": "function",
    "z": "28972163d1638f7e",
    "name": "Hiện cảnh báo",
    "func": "var h = msg.payload.humidity;\nmsg.payload = '🔔 CẢNH BÁO: độ ẩm rất thấp (' + (h != null ? h : '?') + '%) — cần tưới ngay';\nreturn msg;",
    "outputs": 1,
    "timeout": 0,
    "noerr": 0,
    "initialize": "",
    "finalize": "",
    "libs": [],
    "x": 780,
    "y": 660,
    "wires": [
      [
        "ac643c3a74928b73"
      ]
    ]
  },
  {
    "id": "ac643c3a74928b73",
    "type": "ui_text",
    "z": "28972163d1638f7e",
    "group": "d2ca79a83590b557",
    "order": 7,
    "width": "3",
    "height": "2",
    "name": "Cảnh báo Buzzer",
    "format": "<span style=\"font-size:15px;line-height:1.4;color:#b71c1c;font-weight:600\">{{msg.payload}}</span>",
    "layout": "row-center",
    "className": "",
    "style": false,
    "font": "",
    "fontSize": "",
    "color": "",
    "x": 1010,
    "y": 680,
    "wires": []
  },
  {
    "id": "cc5a9fcda823fb39",
    "type": "ui_chart",
    "z": "28972163d1638f7e",
    "name": "Biểu đồ nhiệt độ",
    "group": "d2ca79a83590b557",
    "order": 2,
    "width": "3",
    "height": "4",
    "chartType": "line",
    "outputs": 1,
    "x": 740,
    "y": 500,
    "wires": [
      []
    ]
  },
  {
    "id": "2c3a97d97ea9da30",
    "type": "ui_chart",
    "z": "28972163d1638f7e",
    "name": "Biểu đồ độ ẩm",
    "group": "d2ca79a83590b557",
    "order": 3,
    "width": "3",
    "height": "4",
    "chartType": "line",
    "outputs": 1,
    "x": 740,
    "y": 540,
    "wires": [
      []
    ]
  },
  {
    "id": "9e2f992ea37b88e9",
    "type": "ui_text",
    "z": "28972163d1638f7e",
    "group": "d2ca79a83590b557",
    "order": 4,
    "width": "3",
    "height": 1,
    "name": "Nhiệt độ",
    "format": "🌡 Nhiệt độ<br><span style=\"font-size:24px;font-weight:bold\">{{msg.payload.temperature}}°C</span>",
    "layout": "row-spread",
    "x": 540,
    "y": 200,
    "wires": []
  },
  {
    "id": "ef65ccde2a9dc727",
    "type": "ui_text",
    "z": "28972163d1638f7e",
    "group": "d2ca79a83590b557",
    "order": 5,
    "width": "3",
    "height": 1,
    "name": "Độ ẩm",
    "format": "💧 Độ ẩm<br><span style=\"font-size:24px;font-weight:bold\">{{msg.payload.humidity}}%</span>",
    "layout": "row-spread",
    "x": 530,
    "y": 140,
    "wires": []
  },
  {
    "id": "9782277746682320",
    "type": "ui_button",
    "z": "28972163d1638f7e",
    "name": "Bật/Tắt bơm",
    "group": "22743ae4eedbebe6",
    "order": 1,
    "width": "3",
    "height": 1,
    "label": "Máy bơm",
    "color": "#ffffff",
    "icon": "fa-tint",
    "payload": "{\"pump\":true,\"duration\":5}",
    "payloadType": "json",
    "topic": "farm/control",
    "x": 250,
    "y": 720,
    "wires": [
      [
        "52d4228c218a253a"
      ]
    ]
  },
  {
    "id": "9269adf2dde7a036",
    "type": "ui_switch",
    "z": "28972163d1638f7e",
    "name": "Tưới tự động",
    "label": "Tưới tự động",
    "group": "22743ae4eedbebe6",
    "order": 2,
    "width": "3",
    "height": 1,
    "topic": "",
    "x": 260,
    "y": 800,
    "wires": [
      [
        "f0dd0c472d5d7e77"
      ]
    ]
  },
  {
    "id": "f0dd0c472d5d7e77",
    "type": "change",
    "z": "28972163d1638f7e",
    "name": "Set flow.manual",
    "rules": [
      {
        "t": "set",
        "p": "manual",
        "pt": "flow",
        "to": "payload",
        "tot": "msg"
      }
    ],
    "action": "",
    "property": "",
    "from": "",
    "to": "",
    "reg": false,
    "x": 460,
    "y": 800,
    "wires": [
      []
    ]
  },
  {
    "id": "52d4228c218a253a",
    "type": "mqtt out",
    "z": "28972163d1638f7e",
    "name": "Gửi điều khiển bơm",
    "topic": "farm/control",
    "qos": "0",
    "retain": "false",
    "broker": "d4179fb10b941343",
    "x": 1340,
    "y": 720,
    "wires": []
  },
  {
    "id": "d4179fb10b941343",
    "type": "mqtt-broker",
    "name": "Smart",
    "broker": "b1c8f2cc5cd4416fb74b671a407dc0ff.s1.eu.hivemq.cloud",
    "port": "8883",
    "tls": "",
    "clientid": "",
    "autoConnect": true,
    "usetls": true,
    "protocolVersion": 4,
    "keepalive": 60,
    "cleansession": true,
    "autoUnsubscribe": true,
    "birthTopic": "",
    "birthQos": "0",
    "birthRetain": "false",
    "birthPayload": "",
    "birthMsg": {},
    "closeTopic": "",
    "closeQos": "0",
    "closeRetain": "false",
    "closePayload": "",
    "closeMsg": {},
    "willTopic": "",
    "willQos": "0",
    "willRetain": "false",
    "willPayload": "",
    "willMsg": {},
    "userProps": "",
    "sessionExpiry": ""
  },
  {
    "id": "d2ca79a83590b557",
    "type": "ui_group",
    "name": "Giám sát",
    "tab": "2ec7089e7e446577",
    "order": 1,
    "disp": true,
    "width": "6",
    "className": ""
  },
  {
    "id": "22743ae4eedbebe6",
    "type": "ui_group",
    "name": "Điều khiển",
    "tab": "2ec7089e7e446577",
    "order": 2,
    "disp": true,
    "width": "6",
    "className": ""
  },
  {
    "id": "2ec7089e7e446577",
    "type": "ui_tab",
    "name": "Smart Farm",
    "icon": "fa-leaf",
    "order": 1
  },
  {
    "id": "20efe6ee98805f62",
    "type": "global-config",
    "env": [],
    "modules": {
      "node-red-dashboard": "3.6.6"
    }
  }
]